squimple/__init__.py
squimple/server.py
squimple/static/ace.js
squimple/static/mode-sql.js
squimple/static/style.css
squimple/templates/index.html
squimple-0.0.1.dist-info/entry_points.txt
squimple-0.0.1.dist-info/LICENSE
squimple-0.0.1.dist-info/WHEEL
squimple-0.0.1.dist-info/METADATA
squimple-0.0.1.dist-info/RECORD
