Metadata-Version: 2.1
Name: squimple
Version: 0.0.1
Summary: Simple SQLite Web Interface
Author: Zach Gulde
Author-email: zachgulde@gmail.com
Classifier: License :: OSI Approved :: MIT License
